{
  "voltage_level_id": "JUINEP4",
  "name": "JUINEP4_2021-01-03T15_20_observee",
  "scenario": null,
  "edited": false,
  "mode": "observee",
  "depart": {
    "JUINEP4_JUINE   4BVUE5.2  SA.1": true,
    "JUINEP4_JUINE   4B.REN.1  SA.1": true,
    "JUINEP4_JUINE   4LOGES.3  SA.1": true,
    "JUINEP4_JUINE   4THIO5.2  SA.1": false,
    "JUINEP4_JUINE   4SSEVR.2  SA.1": true,
    "JUINEP4_JUINE   4SEC..32  SS.1.32": false,
    "JUINEP4_JUINE   4LOGES.2  SA.1": false,
    "JUINEP4_JUINE   4TR412    SA.1": true,
    "JUINEP4_JUINE   4SEC..21  SS.1.21": false,
    "JUINEP4_JUINE   4COUPL.2  SA.1": false,
    "JUINEP4_JUINE   4SSEVR.1  SA.1": false,
    "JUINEP4_JUINE   4LOGES.1  SA.1": false,
    "JUINEP4_JUINE   4MORIG.1  SA.1": false,
    "JUINEP4_JUINE   4BVUE5.1  SA.1": false,
    "JUINEP4_JUINE   4TR411    SA.1": false,
    "JUINEP4_JUINE   4BVUE5.2  SA.2": false,
    "JUINEP4_JUINE   4B.REN.1  SA.2": false,
    "JUINEP4_JUINE   4LOGES.3  SA.2": false,
    "JUINEP4_JUINE   4THIO5.2  SA.2": true,
    "JUINEP4_JUINE   4SSEVR.2  SA.2": false,
    "JUINEP4_JUINE   4SEC..32  SS.2.32": false,
    "JUINEP4_JUINE   4LOGES.2  SA.2": true,
    "JUINEP4_JUINE   4TR412    SA.2": false,
    "JUINEP4_JUINE   4SEC..21  SS.2.21": false,
    "JUINEP4_JUINE   4COUPL.2  SA.2": false,
    "JUINEP4_JUINE   4SSEVR.1  SA.2": true,
    "JUINEP4_JUINE   4LOGES.1  SA.2": true,
    "JUINEP4_JUINE   4MORIG.1  SA.2": true,
    "JUINEP4_JUINE   4BVUE5.1  SA.2": true,
    "JUINEP4_JUINE   4TR411    SA.2": true,
    "JUINEP4_JUINE   4B.REN.1  DJ": false,
    "JUINEP4_JUINE   4BVUE5.1  DJ": false,
    "JUINEP4_JUINE   4BVUE5.2  DJ": false,
    "JUINEP4_JUINE   4COUPL.2  DJ": false,
    "JUINEP4_JUINE   4LOGES.1  DJ": false,
    "JUINEP4_JUINE   4LOGES.2  DJ": false,
    "JUINEP4_JUINE   4LOGES.3  DJ": false,
    "JUINEP4_JUINE   4MORIG.1  DJ": false,
    "JUINEP4_JUINE   4SSEVR.1  DJ": false,
    "JUINEP4_JUINE   4SSEVR.2  DJ": false,
    "JUINEP4_JUINE   4THIO5.2  DJ": false,
    "JUINEP4_JUINE   4TR411    DJ.HT": false,
    "JUINEP4_JUINE   4TR412    DJ.HT": false,
    "JUINEP4_JUINE   4TR411    DJ.HT.JUINE TR411": false,
    "JUINEP4_Disj JUINEINF": false,
    "JUINEP4_JUINE   4TR412    DJ.HT.JUINE TR412": false,
    "JUINEP4_Disj JUINEING": false
  },
  "cible": {
    "JUINEP4_JUINE   4BVUE5.2  SA.1": true,
    "JUINEP4_JUINE   4B.REN.1  SA.1": false,
    "JUINEP4_JUINE   4LOGES.3  SA.1": true,
    "JUINEP4_JUINE   4THIO5.2  SA.1": false,
    "JUINEP4_JUINE   4SSEVR.2  SA.1": true,
    "JUINEP4_JUINE   4SEC..32  SS.1.32": true,
    "JUINEP4_JUINE   4LOGES.2  SA.1": false,
    "JUINEP4_JUINE   4TR412    SA.1": true,
    "JUINEP4_JUINE   4SEC..21  SS.1.21": false,
    "JUINEP4_JUINE   4COUPL.2  SA.1": false,
    "JUINEP4_JUINE   4SSEVR.1  SA.1": false,
    "JUINEP4_JUINE   4LOGES.1  SA.1": false,
    "JUINEP4_JUINE   4MORIG.1  SA.1": false,
    "JUINEP4_JUINE   4BVUE5.1  SA.1": false,
    "JUINEP4_JUINE   4TR411    SA.1": false,
    "JUINEP4_JUINE   4BVUE5.2  SA.2": false,
    "JUINEP4_JUINE   4B.REN.1  SA.2": true,
    "JUINEP4_JUINE   4LOGES.3  SA.2": false,
    "JUINEP4_JUINE   4THIO5.2  SA.2": true,
    "JUINEP4_JUINE   4SSEVR.2  SA.2": false,
    "JUINEP4_JUINE   4SEC..32  SS.2.32": false,
    "JUINEP4_JUINE   4LOGES.2  SA.2": true,
    "JUINEP4_JUINE   4TR412    SA.2": false,
    "JUINEP4_JUINE   4SEC..21  SS.2.21": false,
    "JUINEP4_JUINE   4COUPL.2  SA.2": false,
    "JUINEP4_JUINE   4SSEVR.1  SA.2": true,
    "JUINEP4_JUINE   4LOGES.1  SA.2": true,
    "JUINEP4_JUINE   4MORIG.1  SA.2": true,
    "JUINEP4_JUINE   4BVUE5.1  SA.2": true,
    "JUINEP4_JUINE   4TR411    SA.2": true,
    "JUINEP4_JUINE   4B.REN.1  DJ": false,
    "JUINEP4_JUINE   4BVUE5.1  DJ": false,
    "JUINEP4_JUINE   4BVUE5.2  DJ": false,
    "JUINEP4_JUINE   4COUPL.2  DJ": false,
    "JUINEP4_JUINE   4LOGES.1  DJ": false,
    "JUINEP4_JUINE   4LOGES.2  DJ": false,
    "JUINEP4_JUINE   4LOGES.3  DJ": false,
    "JUINEP4_JUINE   4MORIG.1  DJ": false,
    "JUINEP4_JUINE   4SSEVR.1  DJ": false,
    "JUINEP4_JUINE   4SSEVR.2  DJ": false,
    "JUINEP4_JUINE   4THIO5.2  DJ": false,
    "JUINEP4_JUINE   4TR411    DJ.HT": false,
    "JUINEP4_JUINE   4TR412    DJ.HT": false,
    "JUINEP4_JUINE   4TR411    DJ.HT.JUINE TR411": false,
    "JUINEP4_Disj JUINEINF": false,
    "JUINEP4_JUINE   4TR412    DJ.HT.JUINE TR412": false,
    "JUINEP4_Disj JUINEING": false
  },
  "nb_manoeuvres": 7,
  "manoeuvres": [
    {
      "ordre": 1,
      "switch_id": "JUINEP4_JUINE   4B.REN.1  DJ",
      "action": "OPEN",
      "raison": "observée (2021-01-03T15:15)",
      "boucle": null
    },
    {
      "ordre": 2,
      "switch_id": "JUINEP4_JUINE   4B.REN.1  SA.1",
      "action": "CLOSE",
      "raison": "observée (2021-01-03T15:15)",
      "boucle": null
    },
    {
      "ordre": 3,
      "switch_id": "JUINEP4_JUINE   4B.REN.1  SA.2",
      "action": "OPEN",
      "raison": "observée (2021-01-03T15:15)",
      "boucle": null
    },
    {
      "ordre": 4,
      "switch_id": "JUINEP4_JUINE   4SEC..32  SS.1.32",
      "action": "OPEN",
      "raison": "observée (2021-01-03T15:15)",
      "boucle": null
    },
    {
      "ordre": 5,
      "switch_id": "JUINEP4_JUINE   4THIO5.2  DJ",
      "action": "OPEN",
      "raison": "observée (2021-01-03T15:15)",
      "boucle": null
    },
    {
      "ordre": 6,
      "switch_id": "JUINEP4_JUINE   4B.REN.1  DJ",
      "action": "CLOSE",
      "raison": "observée (2021-01-03T15:20)",
      "boucle": null
    },
    {
      "ordre": 7,
      "switch_id": "JUINEP4_JUINE   4THIO5.2  DJ",
      "action": "CLOSE",
      "raison": "observée (2021-01-03T15:20)",
      "boucle": null
    }
  ],
  "meta": {
    "tags": [
      "scission_noeud",
      "sectionnement_barre",
      "reaiguillage_departs"
    ],
    "t_depart": "2021-01-03T15:10",
    "t_cible": "2021-01-03T15:20"
  }
}